fastrlock/__init__.pxd
fastrlock/__init__.py
fastrlock/_lock.pxi
fastrlock/rlock.cpython-39-darwin.so
fastrlock/rlock.pxd
fastrlock/rlock.pyx
fastrlock-0.8.3.dist-info/LICENSE
fastrlock-0.8.3.dist-info/METADATA
fastrlock-0.8.3.dist-info/WHEEL
fastrlock-0.8.3.dist-info/top_level.txt
fastrlock-0.8.3.dist-info/RECORD
