Metadata-Version: 2.1
Name: fastrlock
Version: 0.8.3
Summary: Fast, re-entrant optimistic lock implemented in Cython
Home-page: https://github.com/scoder/fastrlock
Author: Stefan Behnel
Author-email: stefan_ml@behnel.de
License: MIT style
Platform: UNKNOWN
Classifier: Development Status :: 5 - Production/Stable
Classifier: Intended Audience :: Developers
Classifier: Intended Audience :: Information Technology
Classifier: License :: OSI Approved :: MIT License
Classifier: Programming Language :: Cython
Classifier: Programming Language :: Python :: 3
Classifier: Operating System :: OS Independent
Classifier: Topic :: Software Development
